pyreadstat/worker.py
pyreadstat/pyreadstat.cpython-314-darwin.so
pyreadstat/__init__.py
pyreadstat/_readstat_writer.cpython-314-darwin.so
pyreadstat/_readstat_parser.cpython-314-darwin.so
pyreadstat/pyfunctions.py
pyreadstat-1.3.3.dist-info/RECORD
pyreadstat-1.3.3.dist-info/WHEEL
pyreadstat-1.3.3.dist-info/top_level.txt
pyreadstat-1.3.3.dist-info/METADATA
pyreadstat-1.3.3.dist-info/licenses/LICENSE
