Metadata-Version: 2.4
Name: pyreadstat
Version: 1.3.3
Summary: Reads and Writes SAS, SPSS and Stata files into/from pandas and polars data frames.
Home-page: https://github.com/Roche/pyreadstat
Download-URL: https://github.com/Roche/pyreadstat/dist
Author: Otto Fajardo
Author-email: pleasecontactviagithub@notvalid.com
License: Apache-2.0
Classifier: Programming Language :: Python
Classifier: Programming Language :: Cython
Classifier: Programming Language :: C
Classifier: Intended Audience :: Science/Research
Classifier: Topic :: Scientific/Engineering
Classifier: Environment :: Console
License-File: LICENSE
Requires-Dist: narwhals>=2.10.1
Requires-Dist: numpy
Dynamic: author
Dynamic: author-email
Dynamic: classifier
Dynamic: description
Dynamic: description-content-type
Dynamic: download-url
Dynamic: home-page
Dynamic: license
Dynamic: license-file
Dynamic: requires-dist
Dynamic: summary
